processpiper/__init__.py
processpiper/activity.py
processpiper/bpmn.py
processpiper/colourtheme.py
processpiper/constants.py
processpiper/coordinate.py
processpiper/event.py
processpiper/footer.py
processpiper/gateway.py
processpiper/helper.py
processpiper/lane.py
processpiper/layout.py
processpiper/painter.py
processpiper/pool.py
processpiper/processmap.py
processpiper/shape.py
processpiper/text2diagram.py
processpiper/title.py
processpiper/version.py
tests/test_appearance.py
tests/test_bpmn.py
tests/test_case01.py
tests/test_processmapper.py
tests/test_promo.py
tests/test_sample.py
tests/test_text2diagram.py
tests/util_test.py
processpiper-0.8.1.dist-info/LICENSE
processpiper-0.8.1.dist-info/METADATA
processpiper-0.8.1.dist-info/WHEEL
processpiper-0.8.1.dist-info/top_level.txt
processpiper-0.8.1.dist-info/RECORD
