Metadata-Version: 2.1
Name: processpiper
Version: 0.8.1
Summary: Processpiper. An open source python library to generate business process diagram using code.
Author: CS Goh
Project-URL: Homepage, https://github.com/csgoh/processpiper
Project-URL: Bug Tracker, https://github.com/csgoh/processpiper/issues
Classifier: Programming Language :: Python :: 3.10
Classifier: License :: OSI Approved :: MIT License
Classifier: Operating System :: OS Independent
Requires-Python: >=3.10
License-File: LICENSE
Requires-Dist: Pillow >=9.5.0
Requires-Dist: rich >=13.4.2
Requires-Dist: drawsvg >=2.2.0
